structlog_gcp/__about__.py
structlog_gcp/__init__.py
structlog_gcp/base.py
structlog_gcp/constants.py
structlog_gcp/error_reporting.py
structlog_gcp/processors.py
structlog_gcp/py.typed
structlog_gcp-0.5.0.dist-info/METADATA
structlog_gcp-0.5.0.dist-info/WHEEL
structlog_gcp-0.5.0.dist-info/licenses/LICENSE
structlog_gcp-0.5.0.dist-info/RECORD
