Metadata-Version: 2.4
Name: structlog-gcp
Version: 0.5.0
Summary: A structlog set of processors to output as Google Cloud Logging format
Project-URL: Documentation, https://github.com/multani/structlog-gcp#readme
Project-URL: Issues, https://github.com/multani/structlog-gcp/issues
Project-URL: Source, https://github.com/multani/structlog-gcp
Author-email: Jonathan Ballet <jon@multani.info>
License: The MIT License (MIT)
License-File: LICENSE
Classifier: Development Status :: 4 - Beta
Classifier: Programming Language :: Python
Classifier: Programming Language :: Python :: 3.10
Classifier: Programming Language :: Python :: 3.11
Classifier: Programming Language :: Python :: 3.12
Classifier: Programming Language :: Python :: 3.13
Classifier: Programming Language :: Python :: Implementation :: CPython
Classifier: Programming Language :: Python :: Implementation :: PyPy
Requires-Python: >=3.10
Requires-Dist: structlog
